openfile.py
openfile-0.0.7.dist-info/METADATA
openfile-0.0.7.dist-info/RECORD
openfile-0.0.7.dist-info/WHEEL
openfile-0.0.7.dist-info/top_level.txt
