Metadata-Version: 1.1
Name: openfile
Version: 0.0.7
Summary: A convenience function that delegates to the appropriate standard library function.
Home-page: https://github.com/luismsgomes/openfile
Author: Luís Gomes
Author-email: luismsgomes@gmail.com
License: MIT
Keywords: convenience
Platform: UNKNOWN
Classifier: Development Status :: 3 - Alpha
Classifier: License :: OSI Approved :: MIT License
Classifier: Programming Language :: Python :: 3.5
